{
  "report_info": {
    "target": "alx.trading",
    "generation_timestamp": "2025-06-05T23:50:55.793339",
    "report_type": "comprehensive_extraction_analysis",
    "analysis_scope": "all_extraction_attempts"
  },
  "extraction_summary": {
    "total_profile_files": 13,
    "total_session_files": 32,
    "total_databases": 18,
    "total_json_files": 70,
    "real_data_files": 0,
    "total_database_records": 234,
    "credentials_found": false,
    "sessions_found": true,
    "actual_messages_found": false
  },
  "final_verdict": {
    "extraction_successful": false,
    "real_dm_data_found": false,
    "simulation_data_only": true,
    "session_issues": false,
    "recommendations": [
      "All session tokens appear expired or invalid",
      "Instagram login credentials may be incorrect or account locked",
      "Consider using fresh session hijacking techniques",
      "Alternative: Focus on OSINT data collection instead of direct DM access",
      "Check if Instagram has updated their API endpoints"
    ]
  },
  "detailed_findings": {
    "profile_data": [
      {
        "file": "/workspaces/sugarglitch-realops/advanced_dm_report_alx.trading_20250605_222448.json",
        "size": 672,
        "modified": "2025-06-05T22:24:48.137883",
        "contains_target": true
      },
      {
        "file": "/workspaces/sugarglitch-realops/advanced_dm_report_alx.trading_20250605_222924.json",
        "size": 672,
        "modified": "2025-06-05T22:29:24.304889",
        "contains_target": true
      },
      {
        "file": "/workspaces/sugarglitch-realops/ultimate_dm_report_alx.trading_20250605_211352.json",
        "size": 432,
        "modified": "2025-06-05T21:13:52.234789",
        "contains_target": true
      },
      {
        "file": "/workspaces/sugarglitch-realops/ultimate_dm_report_alx.trading_20250605_220819.json",
        "size": 432,
        "modified": "2025-06-05T22:08:19.623861",
        "contains_target": true
      },
      {
        "file": "/workspaces/sugarglitch-realops/advanced_dm_report_alx.trading_20250605_224538.json",
        "size": 672,
        "modified": "2025-06-05T22:45:38.558911",
        "contains_target": true
      },
      {
        "file": "/workspaces/sugarglitch-realops/ultimate_dm_report_alx.trading_20250605_195247.json",
        "size": 432,
        "modified": "2025-06-05T19:52:47.691682",
        "contains_target": true
      },
      {
        "file": "/workspaces/sugarglitch-realops/advanced_dm_report_alx.trading_20250605_224955.json",
        "size": 672,
        "modified": "2025-06-05T22:49:55.114916",
        "contains_target": true
      },
      {
        "file": "/workspaces/sugarglitch-realops/config/json/MASTER_PROFILE_alx_trading_1748262733.json",
        "size": 2199,
        "modified": "2025-06-02T23:24:09.730629",
        "contains_target": true
      },
      {
        "file": "/workspaces/sugarglitch-realops/config/json/MASTER_PROFILE_alx_trading_1748264047.json",
        "size": 2896,
        "modified": "2025-06-02T23:24:09.730629",
        "contains_target": true
      },
      {
        "file": "/workspaces/sugarglitch-realops/config/json/INTIMATE_MESSAGES_alx.trading_1748264946.json",
        "size": 322,
        "modified": "2025-06-02T23:24:09.730629",
        "contains_target": true
      },
      {
        "file": "/workspaces/sugarglitch-realops/reports/MASTER_OPERATION_REPORT_MASTER_OP_1748818144.json",
        "size": 846,
        "modified": "2025-06-02T23:24:09.741629",
        "contains_target": true
      },
      {
        "file": "/workspaces/sugarglitch-realops/config/json/MASTER_PROFILE_alx_trading_1748262733.json",
        "size": 2199,
        "modified": "2025-06-02T23:24:09.730629",
        "contains_target": true
      },
      {
        "file": "/workspaces/sugarglitch-realops/config/json/MASTER_PROFILE_alx_trading_1748264047.json",
        "size": 2896,
        "modified": "2025-06-02T23:24:09.730629",
        "contains_target": true
      }
    ],
    "session_files": [
      {
        "file": "/workspaces/sugarglitch-realops/sessions/mitmproxy-dhparam.pem",
        "size": 770,
        "type": "sessions"
      },
      {
        "file": "/workspaces/sugarglitch-realops/sessions/session-alx.trading",
        "size": 70,
        "type": "sessions"
      },
      {
        "file": "/workspaces/sugarglitch-realops/sessions/mitmproxy-ca-cert.pem",
        "size": 1172,
        "type": "sessions"
      },
      {
        "file": "/workspaces/sugarglitch-realops/sessions/mitmproxy-ca-cert.cer",
        "size": 1172,
        "type": "sessions"
      },
      {
        "file": "/workspaces/sugarglitch-realops/sessions/quick_bypass_session.json",
        "size": 194,
        "type": "sessions"
      },
      {
        "file": "/workspaces/sugarglitch-realops/sessions/mitmproxy-ca-cert.p12",
        "size": 1035,
        "type": "sessions"
      },
      {
        "file": "/workspaces/sugarglitch-realops/sessions/mitmproxy-ca.pem",
        "size": 2847,
        "type": "sessions"
      },
      {
        "file": "/workspaces/sugarglitch-realops/sessions/mitmproxy-ca.p12",
        "size": 2411,
        "type": "sessions"
      },
      {
        "file": "/workspaces/sugarglitch-realops/hijacked_sessions/ip_spoofed_session_1749156465.json",
        "size": 21,
        "type": "hijacked_sessions"
      },
      {
        "file": "/workspaces/sugarglitch-realops/hijacked_sessions/rotated_session_1749156585.json",
        "size": 24,
        "type": "hijacked_sessions"
      },
      {
        "file": "/workspaces/sugarglitch-realops/hijacked_sessions/bypass_report_1749159283.json",
        "size": 199,
        "type": "hijacked_sessions"
      },
      {
        "file": "/workspaces/sugarglitch-realops/hijacked_sessions/rotated_session_1749156592.json",
        "size": 24,
        "type": "hijacked_sessions"
      },
      {
        "file": "/workspaces/sugarglitch-realops/hijacked_sessions/spoofed_session_1749156447.json",
        "size": 21,
        "type": "hijacked_sessions"
      },
      {
        "file": "/workspaces/sugarglitch-realops/hijacked_sessions/ip_spoofed_session_1749156467.json",
        "size": 21,
        "type": "hijacked_sessions"
      },
      {
        "file": "/workspaces/sugarglitch-realops/hijacked_sessions/rotated_session_1749156572.json",
        "size": 24,
        "type": "hijacked_sessions"
      },
      {
        "file": "/workspaces/sugarglitch-realops/hijacked_sessions/ip_spoofed_session_1749156458.json",
        "size": 21,
        "type": "hijacked_sessions"
      },
      {
        "file": "/workspaces/sugarglitch-realops/hijacked_sessions/rotated_session_1749156575.json",
        "size": 24,
        "type": "hijacked_sessions"
      },
      {
        "file": "/workspaces/sugarglitch-realops/hijacked_sessions/spoofed_session_1749156441.json",
        "size": 21,
        "type": "hijacked_sessions"
      },
      {
        "file": "/workspaces/sugarglitch-realops/hijacked_sessions/rotated_session_1749156565.json",
        "size": 24,
        "type": "hijacked_sessions"
      },
      {
        "file": "/workspaces/sugarglitch-realops/hijacked_sessions/ip_spoofed_session_1749156461.json",
        "size": 21,
        "type": "hijacked_sessions"
      },
      {
        "file": "/workspaces/sugarglitch-realops/hijacked_sessions/spoofed_session_1749156443.json",
        "size": 21,
        "type": "hijacked_sessions"
      },
      {
        "file": "/workspaces/sugarglitch-realops/hijacked_sessions/rotated_session_1749156567.json",
        "size": 24,
        "type": "hijacked_sessions"
      },
      {
        "file": "/workspaces/sugarglitch-realops/hijacked_sessions/rotated_session_1749156562.json",
        "size": 24,
        "type": "hijacked_sessions"
      },
      {
        "file": "/workspaces/sugarglitch-realops/hijacked_sessions/rotated_session_1749156582.json",
        "size": 24,
        "type": "hijacked_sessions"
      },
      {
        "file": "/workspaces/sugarglitch-realops/hijacked_sessions/spoofed_session_1749156450.json",
        "size": 21,
        "type": "hijacked_sessions"
      },
      {
        "file": "/workspaces/sugarglitch-realops/hijacked_sessions/rotated_session_1749156578.json",
        "size": 24,
        "type": "hijacked_sessions"
      },
      {
        "file": "/workspaces/sugarglitch-realops/hijacked_sessions/hijacked_session_1749156763.json",
        "size": 21,
        "type": "hijacked_sessions"
      },
      {
        "file": "/workspaces/sugarglitch-realops/hijacked_sessions/bypass_report_1749156656.json",
        "size": 162,
        "type": "hijacked_sessions"
      },
      {
        "file": "/workspaces/sugarglitch-realops/hijacked_sessions/spoofed_session_1749156453.json",
        "size": 21,
        "type": "hijacked_sessions"
      },
      {
        "file": "/workspaces/sugarglitch-realops/hijacked_sessions/hijacked_session_1749156438.json",
        "size": 21,
        "type": "hijacked_sessions"
      },
      {
        "file": "/workspaces/sugarglitch-realops/hijacked_sessions/ip_spoofed_session_1749156463.json",
        "size": 21,
        "type": "hijacked_sessions"
      },
      {
        "file": "/workspaces/sugarglitch-realops/hijacked_sessions/rotated_session_1749156589.json",
        "size": 24,
        "type": "hijacked_sessions"
      }
    ],
    "extraction_attempts": [],
    "hijacked_sessions": [],
    "bypass_reports": [
      {
        "file": "/workspaces/sugarglitch-realops/reports/session_security_test_1749154282.json",
        "size": 2430,
        "contains_tokens": false,
        "contains_sessions": true
      },
      {
        "file": "/workspaces/sugarglitch-realops/reports/intelligence_report_alx.trading_1748818144.json",
        "size": 121,
        "contains_tokens": false,
        "contains_sessions": false
      },
      {
        "file": "/workspaces/sugarglitch-realops/reports/instagram_session_analysis_1749154258.json",
        "size": 2936,
        "contains_tokens": false,
        "contains_sessions": true
      },
      {
        "file": "/workspaces/sugarglitch-realops/reports/intelligence_report_whatilove1728_1748818144.json",
        "size": 121,
        "contains_tokens": false,
        "contains_sessions": false
      },
      {
        "file": "/workspaces/sugarglitch-realops/reports/MASTER_OPERATION_REPORT_MASTER_OP_1748818144.json",
        "size": 846,
        "contains_tokens": false,
        "contains_sessions": true
      },
      {
        "file": "/workspaces/sugarglitch-realops/reports/session_bypass/advanced_bypass_assessment_20250605_212705.json",
        "size": 5862,
        "contains_tokens": true,
        "contains_sessions": true
      },
      {
        "file": "/workspaces/sugarglitch-realops/reports/session_bypass/advanced_bypass_assessment_20250605_213251.json",
        "size": 5864,
        "contains_tokens": true,
        "contains_sessions": true
      },
      {
        "file": "/workspaces/sugarglitch-realops/reports/hijacking_tests/hijacking_assessment_report_20250605_205805.json",
        "size": 398,
        "contains_tokens": false,
        "contains_sessions": true
      },
      {
        "file": "/workspaces/sugarglitch-realops/reports/hijacking_tests/cookie_theft_results_20250605_213303.json",
        "size": 95,
        "contains_tokens": false,
        "contains_sessions": false
      },
      {
        "file": "/workspaces/sugarglitch-realops/reports/hijacking_tests/mitm_attack_results_20250605_213307.json",
        "size": 142,
        "contains_tokens": false,
        "contains_sessions": false
      },
      {
        "file": "/workspaces/sugarglitch-realops/reports/hijacking_tests/session_fixation_results_20250605_205758.json",
        "size": 209,
        "contains_tokens": false,
        "contains_sessions": true
      },
      {
        "file": "/workspaces/sugarglitch-realops/reports/hijacking_tests/session_fixation_results_20250605_213303.json",
        "size": 210,
        "contains_tokens": false,
        "contains_sessions": true
      },
      {
        "file": "/workspaces/sugarglitch-realops/reports/hijacking_tests/cookie_theft_results_20250605_205758.json",
        "size": 94,
        "contains_tokens": false,
        "contains_sessions": false
      },
      {
        "file": "/workspaces/sugarglitch-realops/reports/hijacking_tests/mitm_attack_results_20250605_205805.json",
        "size": 142,
        "contains_tokens": false,
        "contains_sessions": false
      },
      {
        "file": "/workspaces/sugarglitch-realops/reports/hijacking_tests/hijacking_assessment_report_20250605_213307.json",
        "size": 397,
        "contains_tokens": false,
        "contains_sessions": true
      }
    ],
    "databases": [
      {
        "file": "/workspaces/sugarglitch-realops/integrated_targets_2025.db",
        "tables": [
          "targets",
          "sqlite_sequence",
          "operations",
          "extracted_data",
          "target_relationships",
          "monitoring"
        ],
        "total_records": 0,
        "size": 32768
      },
      {
        "file": "/workspaces/sugarglitch-realops/data/operations.db",
        "tables": [
          "operations",
          "sqlite_sequence",
          "messages",
          "sessions",
          "targets",
          "system_logs"
        ],
        "total_records": 13,
        "size": 94208
      },
      {
        "file": "/workspaces/sugarglitch-realops/data/demo_targets.db",
        "tables": [
          "targets",
          "sqlite_sequence",
          "operations",
          "extracted_data",
          "target_relationships",
          "monitoring"
        ],
        "total_records": 5,
        "size": 32768
      },
      {
        "file": "/workspaces/sugarglitch-realops/data/integrated_targets_2025.db",
        "tables": [
          "targets",
          "sqlite_sequence",
          "operations",
          "extracted_data",
          "target_relationships",
          "monitoring",
          "dm_extraction_results"
        ],
        "total_records": 21,
        "size": 65536
      },
      {
        "file": "/workspaces/sugarglitch-realops/data/alx_trading_dms_direct.db",
        "tables": [
          "dm_threads",
          "dm_messages"
        ],
        "total_records": 0,
        "size": 20480
      },
      {
        "file": "/workspaces/sugarglitch-realops/data/backup_20250605_234820.db",
        "tables": [
          "operations",
          "sqlite_sequence",
          "messages",
          "sessions",
          "targets",
          "system_logs"
        ],
        "total_records": 4,
        "size": 94208
      },
      {
        "file": "/workspaces/sugarglitch-realops/data/project_operations.db",
        "tables": [
          "targets",
          "sqlite_sequence",
          "operations",
          "extracted_data",
          "target_relationships",
          "monitoring",
          "dms",
          "personal_data"
        ],
        "total_records": 123,
        "size": 57344
      },
      {
        "file": "/workspaces/sugarglitch-realops/data/session_security.db",
        "tables": [
          "session_tests",
          "intercepted_sessions"
        ],
        "total_records": 0,
        "size": 12288
      },
      {
        "file": "/workspaces/sugarglitch-realops/data/alx_trading_dms.db",
        "tables": [
          "dm_messages",
          "sqlite_sequence",
          "dm_threads"
        ],
        "total_records": 0,
        "size": 24576
      },
      {
        "file": "/workspaces/sugarglitch-realops/data/real_operations.db",
        "tables": [
          "real_targets",
          "sqlite_sequence",
          "intercepted_traffic",
          "extracted_sessions",
          "real_dms",
          "extraction_logs"
        ],
        "total_records": 8,
        "size": 32768
      },
      {
        "file": "/workspaces/sugarglitch-realops/data/real_intercepted_data.db",
        "tables": [
          "real_sessions",
          "sqlite_sequence",
          "real_auth_data",
          "real_api_calls",
          "real_trading_data"
        ],
        "total_records": 0,
        "size": 24576
      },
      {
        "file": "/workspaces/sugarglitch-realops/data/alx_trading_advanced/advanced_extraction.db",
        "tables": [
          "extraction_attempts",
          "sqlite_sequence",
          "dm_data"
        ],
        "total_records": 7,
        "size": 16384
      },
      {
        "file": "/workspaces/sugarglitch-realops/data/injection_extraction/injection_dms.db",
        "tables": [
          "injection_attempts",
          "sqlite_sequence",
          "extracted_messages"
        ],
        "total_records": 5,
        "size": 20480
      },
      {
        "file": "/workspaces/sugarglitch-realops/data/real_alx_dms/real_dm_data.db",
        "tables": [
          "real_dm_threads",
          "real_dm_messages"
        ],
        "total_records": 0,
        "size": 20480
      },
      {
        "file": "/workspaces/sugarglitch-realops/data/real_hijacked_extraction/real_hijacked_dms.db",
        "tables": [
          "real_dm_threads",
          "real_dm_messages",
          "session_tests"
        ],
        "total_records": 7,
        "size": 28672
      },
      {
        "file": "/workspaces/sugarglitch-realops/data/final_alx_extraction/final_dm_data.db",
        "tables": [
          "dm_threads",
          "dm_messages",
          "profile_data"
        ],
        "total_records": 5,
        "size": 28672
      },
      {
        "file": "/workspaces/sugarglitch-realops/data/working_extraction/working_alx_dms.db",
        "tables": [
          "dm_threads",
          "dm_messages",
          "extraction_log",
          "sqlite_sequence"
        ],
        "total_records": 36,
        "size": 61440
      },
      {
        "file": "/workspaces/sugarglitch-realops/data/real_alx_extraction/real_alx_dms.db",
        "tables": [
          "real_extractions",
          "sqlite_sequence",
          "real_dm_threads",
          "real_dm_messages"
        ],
        "total_records": 0,
        "size": 28672
      }
    ],
    "json_files": [
      {
        "file": "/workspaces/sugarglitch-realops/ultimate_dm_extraction_alx.trading_20250605_211352.json",
        "size": 2,
        "message_count": 0,
        "is_real_data": false,
        "modified": "2025-06-05T21:13:52.233789"
      },
      {
        "file": "/workspaces/sugarglitch-realops/ultimate_dm_extraction_alx.trading_20250605_195247.json",
        "size": 2,
        "message_count": 0,
        "is_real_data": false,
        "modified": "2025-06-05T19:52:47.691682"
      },
      {
        "file": "/workspaces/sugarglitch-realops/advanced_dm_extraction_alx.trading_20250605_222448.json",
        "size": 2,
        "message_count": 0,
        "is_real_data": false,
        "modified": "2025-06-05T22:24:48.137883"
      },
      {
        "file": "/workspaces/sugarglitch-realops/advanced_dm_extraction_alx.trading_20250605_224955.json",
        "size": 2,
        "message_count": 0,
        "is_real_data": false,
        "modified": "2025-06-05T22:49:55.114916"
      },
      {
        "file": "/workspaces/sugarglitch-realops/ultimate_dm_extraction_alx.trading_20250605_220819.json",
        "size": 2,
        "message_count": 0,
        "is_real_data": false,
        "modified": "2025-06-05T22:08:19.623861"
      },
      {
        "file": "/workspaces/sugarglitch-realops/advanced_dm_extraction_alx.trading_20250605_224538.json",
        "size": 2,
        "message_count": 0,
        "is_real_data": false,
        "modified": "2025-06-05T22:45:38.557911"
      },
      {
        "file": "/workspaces/sugarglitch-realops/advanced_dm_extraction_alx.trading_20250605_222924.json",
        "size": 2,
        "message_count": 0,
        "is_real_data": false,
        "modified": "2025-06-05T22:29:24.304889"
      },
      {
        "file": "/workspaces/sugarglitch-realops/master_extraction_results/master_extraction_report_1749152655.json",
        "size": 4219,
        "message_count": 0,
        "is_real_data": false,
        "modified": "2025-06-05T19:44:15.946671"
      },
      {
        "file": "/workspaces/sugarglitch-realops/master_extraction_results/master_extraction_report_1749160162.json",
        "size": 4219,
        "message_count": 0,
        "is_real_data": false,
        "modified": "2025-06-05T21:49:22.509836"
      },
      {
        "file": "/workspaces/sugarglitch-realops/master_extraction_results/master_extraction_report_1749153547.json",
        "size": 4219,
        "message_count": 0,
        "is_real_data": false,
        "modified": "2025-06-05T19:59:07.587691"
      },
      {
        "file": "/workspaces/sugarglitch-realops/master_extraction_results/master_extraction_report_1749153355.json",
        "size": 4219,
        "message_count": 0,
        "is_real_data": false,
        "modified": "2025-06-05T19:55:55.619687"
      },
      {
        "file": "/workspaces/sugarglitch-realops/master_extraction_results/master_extraction_report_1749159930.json",
        "size": 4219,
        "message_count": 0,
        "is_real_data": false,
        "modified": "2025-06-05T21:45:30.242831"
      },
      {
        "file": "/workspaces/sugarglitch-realops/master_extraction_results/master_extraction_report_1749158682.json",
        "size": 4219,
        "message_count": 0,
        "is_real_data": false,
        "modified": "2025-06-05T21:24:42.046804"
      },
      {
        "file": "/workspaces/sugarglitch-realops/master_extraction_results/master_extraction_report_1749160517.json",
        "size": 4219,
        "message_count": 0,
        "is_real_data": false,
        "modified": "2025-06-05T21:55:17.136844"
      },
      {
        "file": "/workspaces/sugarglitch-realops/master_extraction_results/master_extraction_report_1749157751.json",
        "size": 4219,
        "message_count": 0,
        "is_real_data": false,
        "modified": "2025-06-05T21:09:11.430783"
      },
      {
        "file": "/workspaces/sugarglitch-realops/master_extraction_results/master_extraction_report_1749157626.json",
        "size": 4219,
        "message_count": 0,
        "is_real_data": false,
        "modified": "2025-06-05T21:07:06.237781"
      },
      {
        "file": "/workspaces/sugarglitch-realops/master_extraction_results/master_extraction_report_1749152816.json",
        "size": 4219,
        "message_count": 0,
        "is_real_data": false,
        "modified": "2025-06-05T19:46:56.447675"
      },
      {
        "file": "/workspaces/sugarglitch-realops/data/dm_extraction_results_20250605_160153.json",
        "size": 926647,
        "message_count": 0,
        "is_real_data": false,
        "modified": "2025-06-05T16:01:53.761588"
      },
      {
        "file": "/workspaces/sugarglitch-realops/data/real_dm_extraction_1748948002.json",
        "size": 270,
        "message_count": 0,
        "is_real_data": false,
        "modified": "2025-06-03T10:53:22.452538"
      },
      {
        "file": "/workspaces/sugarglitch-realops/data/emergency_extraction_plan_20250603_000134.json",
        "size": 1045,
        "message_count": 0,
        "is_real_data": false,
        "modified": "2025-06-03T00:01:34.651542"
      },
      {
        "file": "/workspaces/sugarglitch-realops/data/advanced_extraction_1748949071.json",
        "size": 21508,
        "message_count": 0,
        "is_real_data": false,
        "modified": "2025-06-03T11:11:11.914501"
      },
      {
        "file": "/workspaces/sugarglitch-realops/data/intelligence/instagram_extraction_whatilove1728_20250526_043438.json",
        "size": 777,
        "message_count": 0,
        "is_real_data": false,
        "modified": "2025-06-02T23:24:09.735629"
      },
      {
        "file": "/workspaces/sugarglitch-realops/data/alx_trading_advanced/extraction_results_20250605_220939.json",
        "size": 73,
        "message_count": 0,
        "is_real_data": false,
        "modified": "2025-06-05T22:09:39.521863"
      },
      {
        "file": "/workspaces/sugarglitch-realops/data/alx_trading/real_messages_extraction_1748948322.json",
        "size": 4493,
        "message_count": 0,
        "is_real_data": false,
        "modified": "2025-06-03T10:58:42.008527"
      },
      {
        "file": "/workspaces/sugarglitch-realops/data/alx_trading_dms/dm_extraction_results_1748944727.json",
        "size": 1873,
        "message_count": 0,
        "is_real_data": false,
        "modified": "2025-06-03T09:58:47.089942"
      },
      {
        "file": "/workspaces/sugarglitch-realops/data/alx_trading_dms/dm_extraction_results_1748947846.json",
        "size": 1688,
        "message_count": 0,
        "is_real_data": false,
        "modified": "2025-06-03T10:50:46.456543"
      },
      {
        "file": "/workspaces/sugarglitch-realops/data/alx_trading_dms/dm_extraction_results_1748947559.json",
        "size": 1873,
        "message_count": 0,
        "is_real_data": false,
        "modified": "2025-06-03T10:45:59.816554"
      },
      {
        "file": "/workspaces/sugarglitch-realops/data/alx_trading_dms/dm_extraction_results_1748944667.json",
        "size": 1873,
        "message_count": 0,
        "is_real_data": false,
        "modified": "2025-06-03T09:57:47.326942"
      },
      {
        "file": "/workspaces/sugarglitch-realops/data/alx_trading_dms/dm_extraction_results_1748944217.json",
        "size": 1873,
        "message_count": 0,
        "is_real_data": false,
        "modified": "2025-06-03T09:50:17.559947"
      },
      {
        "file": "/workspaces/sugarglitch-realops/data/working_extraction/working_extraction_report_20250605_231020.json",
        "size": 2950,
        "message_count": 0,
        "is_real_data": false,
        "modified": "2025-06-05T23:10:20.244943"
      },
      {
        "file": "/workspaces/sugarglitch-realops/data/working_extraction/working_extraction_report_20250605_231016.json",
        "size": 2950,
        "message_count": 0,
        "is_real_data": false,
        "modified": "2025-06-05T23:10:16.770943"
      },
      {
        "file": "/workspaces/sugarglitch-realops/data/working_extraction/working_extraction_report_20250605_231018.json",
        "size": 2950,
        "message_count": 0,
        "is_real_data": false,
        "modified": "2025-06-05T23:10:18.476943"
      },
      {
        "file": "/workspaces/sugarglitch-realops/data/working_extraction/working_extraction_report_20250605_230634.json",
        "size": 2950,
        "message_count": 0,
        "is_real_data": false,
        "modified": "2025-06-05T23:06:34.235938"
      },
      {
        "file": "/workspaces/sugarglitch-realops/data/working_extraction/working_extraction_report_20250605_230621.json",
        "size": 2950,
        "message_count": 0,
        "is_real_data": false,
        "modified": "2025-06-05T23:06:21.393938"
      },
      {
        "file": "/workspaces/sugarglitch-realops/data/extractions/ALX_TRADING_ADVANCED_DMS_20250527_041729/extraction_summary.json",
        "size": 835,
        "message_count": 0,
        "is_real_data": false,
        "modified": "2025-06-02T23:24:09.734629"
      },
      {
        "file": "/workspaces/sugarglitch-realops/real_extraction/alx_trading_advanced/advanced_real_extraction_1749153285.json",
        "size": 2458,
        "message_count": 0,
        "is_real_data": false,
        "modified": "2025-06-05T19:54:45.674685"
      },
      {
        "file": "/workspaces/sugarglitch-realops/real_extraction/alx_trading_advanced/advanced_real_extraction_1749152585.json",
        "size": 2458,
        "message_count": 0,
        "is_real_data": false,
        "modified": "2025-06-05T19:43:05.902670"
      },
      {
        "file": "/workspaces/sugarglitch-realops/real_extraction/alx_trading_advanced/advanced_real_extraction_1749160096.json",
        "size": 2458,
        "message_count": 0,
        "is_real_data": false,
        "modified": "2025-06-05T21:48:16.454835"
      },
      {
        "file": "/workspaces/sugarglitch-realops/real_extraction/alx_trading_advanced/advanced_real_extraction_1749157567.json",
        "size": 2458,
        "message_count": 0,
        "is_real_data": false,
        "modified": "2025-06-05T21:06:07.769779"
      },
      {
        "file": "/workspaces/sugarglitch-realops/real_extraction/alx_trading_advanced/advanced_real_extraction_1749158621.json",
        "size": 2458,
        "message_count": 0,
        "is_real_data": false,
        "modified": "2025-06-05T21:23:41.604802"
      },
      {
        "file": "/workspaces/sugarglitch-realops/real_extraction/alx_trading_advanced/advanced_real_extraction_1749157688.json",
        "size": 2458,
        "message_count": 0,
        "is_real_data": false,
        "modified": "2025-06-05T21:08:08.535782"
      },
      {
        "file": "/workspaces/sugarglitch-realops/real_extraction/alx_trading_advanced/advanced_real_extraction_1749152751.json",
        "size": 2458,
        "message_count": 0,
        "is_real_data": false,
        "modified": "2025-06-05T19:45:51.992673"
      },
      {
        "file": "/workspaces/sugarglitch-realops/real_extraction/alx_trading_advanced/advanced_real_extraction_1749153478.json",
        "size": 2458,
        "message_count": 0,
        "is_real_data": false,
        "modified": "2025-06-05T19:57:58.248689"
      },
      {
        "file": "/workspaces/sugarglitch-realops/real_extraction/alx_trading_advanced/advanced_real_extraction_1749154766.json",
        "size": 2458,
        "message_count": 0,
        "is_real_data": false,
        "modified": "2025-06-05T20:19:26.618718"
      },
      {
        "file": "/workspaces/sugarglitch-realops/real_extraction/alx_trading_advanced/advanced_real_extraction_1749160448.json",
        "size": 2458,
        "message_count": 0,
        "is_real_data": false,
        "modified": "2025-06-05T21:54:08.179843"
      },
      {
        "file": "/workspaces/sugarglitch-realops/real_extraction/alx_trading_advanced/advanced_real_extraction_1749159872.json",
        "size": 2458,
        "message_count": 0,
        "is_real_data": false,
        "modified": "2025-06-05T21:44:32.518830"
      },
      {
        "file": "/workspaces/sugarglitch-realops/real_extraction/alx_trading/real_dm_extraction_1749160438.json",
        "size": 270,
        "message_count": 0,
        "is_real_data": false,
        "modified": "2025-06-05T21:53:58.903842"
      },
      {
        "file": "/workspaces/sugarglitch-realops/real_extraction/alx_trading/real_dm_extraction_1749158610.json",
        "size": 270,
        "message_count": 0,
        "is_real_data": false,
        "modified": "2025-06-05T21:23:30.798802"
      },
      {
        "file": "/workspaces/sugarglitch-realops/real_extraction/alx_trading/real_dm_extraction_1749159862.json",
        "size": 270,
        "message_count": 0,
        "is_real_data": false,
        "modified": "2025-06-05T21:44:22.947830"
      },
      {
        "file": "/workspaces/sugarglitch-realops/real_extraction/alx_trading/real_dm_extraction_1749152575.json",
        "size": 270,
        "message_count": 0,
        "is_real_data": false,
        "modified": "2025-06-05T19:42:55.810669"
      },
      {
        "file": "/workspaces/sugarglitch-realops/real_extraction/alx_trading/real_dm_extraction_1749154754.json",
        "size": 270,
        "message_count": 0,
        "is_real_data": false,
        "modified": "2025-06-05T20:19:14.810717"
      },
      {
        "file": "/workspaces/sugarglitch-realops/real_extraction/alx_trading/real_dm_extraction_1749153273.json",
        "size": 270,
        "message_count": 0,
        "is_real_data": false,
        "modified": "2025-06-05T19:54:33.611685"
      },
      {
        "file": "/workspaces/sugarglitch-realops/real_extraction/alx_trading/real_dm_extraction_1749157678.json",
        "size": 270,
        "message_count": 0,
        "is_real_data": false,
        "modified": "2025-06-05T21:07:58.512782"
      },
      {
        "file": "/workspaces/sugarglitch-realops/real_extraction/alx_trading/real_dm_extraction_1749160086.json",
        "size": 270,
        "message_count": 0,
        "is_real_data": false,
        "modified": "2025-06-05T21:48:06.493835"
      },
      {
        "file": "/workspaces/sugarglitch-realops/real_extraction/alx_trading/real_dm_extraction_1749152741.json",
        "size": 270,
        "message_count": 0,
        "is_real_data": false,
        "modified": "2025-06-05T19:45:41.917673"
      },
      {
        "file": "/workspaces/sugarglitch-realops/real_extraction/alx_trading/real_dm_extraction_1749157558.json",
        "size": 270,
        "message_count": 0,
        "is_real_data": false,
        "modified": "2025-06-05T21:05:58.527779"
      },
      {
        "file": "/workspaces/sugarglitch-realops/real_extraction/alx_trading/real_dm_extraction_1749153468.json",
        "size": 270,
        "message_count": 0,
        "is_real_data": false,
        "modified": "2025-06-05T19:57:48.838689"
      },
      {
        "file": "/workspaces/sugarglitch-realops/src/alx_trading_advanced/advanced_real_extraction_1748948092.json",
        "size": 2492,
        "message_count": 0,
        "is_real_data": false,
        "modified": "2025-06-03T10:54:52.616535"
      },
      {
        "file": "/workspaces/sugarglitch-realops/src/alx_trading/actual_extraction_1748948655.json",
        "size": 443,
        "message_count": 0,
        "is_real_data": false,
        "modified": "2025-06-03T11:04:15.659515"
      },
      {
        "file": "/workspaces/sugarglitch-realops/actual_extraction/alx_trading/actual_extraction_1749153277.json",
        "size": 443,
        "message_count": 0,
        "is_real_data": false,
        "modified": "2025-06-05T19:54:37.371685"
      },
      {
        "file": "/workspaces/sugarglitch-realops/actual_extraction/alx_trading/actual_extraction_1749152745.json",
        "size": 443,
        "message_count": 0,
        "is_real_data": false,
        "modified": "2025-06-05T19:45:45.676673"
      },
      {
        "file": "/workspaces/sugarglitch-realops/actual_extraction/alx_trading/actual_extraction_1749157681.json",
        "size": 443,
        "message_count": 0,
        "is_real_data": false,
        "modified": "2025-06-05T21:08:01.185782"
      },
      {
        "file": "/workspaces/sugarglitch-realops/actual_extraction/alx_trading/actual_extraction_1749158614.json",
        "size": 443,
        "message_count": 0,
        "is_real_data": false,
        "modified": "2025-06-05T21:23:34.552802"
      },
      {
        "file": "/workspaces/sugarglitch-realops/actual_extraction/alx_trading/actual_extraction_1749152579.json",
        "size": 443,
        "message_count": 0,
        "is_real_data": false,
        "modified": "2025-06-05T19:42:59.575670"
      },
      {
        "file": "/workspaces/sugarglitch-realops/actual_extraction/alx_trading/actual_extraction_1749159866.json",
        "size": 443,
        "message_count": 0,
        "is_real_data": false,
        "modified": "2025-06-05T21:44:26.699830"
      },
      {
        "file": "/workspaces/sugarglitch-realops/actual_extraction/alx_trading/actual_extraction_1749154758.json",
        "size": 443,
        "message_count": 0,
        "is_real_data": false,
        "modified": "2025-06-05T20:19:18.554717"
      },
      {
        "file": "/workspaces/sugarglitch-realops/actual_extraction/alx_trading/actual_extraction_1749153471.json",
        "size": 443,
        "message_count": 0,
        "is_real_data": false,
        "modified": "2025-06-05T19:57:51.813689"
      },
      {
        "file": "/workspaces/sugarglitch-realops/actual_extraction/alx_trading/actual_extraction_1749160441.json",
        "size": 443,
        "message_count": 0,
        "is_real_data": false,
        "modified": "2025-06-05T21:54:01.485842"
      },
      {
        "file": "/workspaces/sugarglitch-realops/actual_extraction/alx_trading/actual_extraction_1749160090.json",
        "size": 443,
        "message_count": 0,
        "is_real_data": false,
        "modified": "2025-06-05T21:48:10.267835"
      },
      {
        "file": "/workspaces/sugarglitch-realops/actual_extraction/alx_trading/actual_extraction_1749157561.json",
        "size": 443,
        "message_count": 0,
        "is_real_data": false,
        "modified": "2025-06-05T21:06:01.527779"
      }
    ],
    "real_data_found": []
  },
  "conclusion": {
    "real_dm_data_extracted": false,
    "total_extraction_attempts": 70,
    "session_validity": true,
    "primary_issues": [
      "All session tokens appear expired or invalid",
      "Instagram login credentials may be incorrect or account locked",
      "Consider using fresh session hijacking techniques"
    ]
  }
}